djURLs-0.0.2.dist-info/DESCRIPTION.rst
djURLs-0.0.2.dist-info/METADATA
djURLs-0.0.2.dist-info/RECORD
djURLs-0.0.2.dist-info/WHEEL
djURLs-0.0.2.dist-info/metadata.json
djURLs-0.0.2.dist-info/top_level.txt
djurls/__init__.py
djurls/config.py
djurls/decorators.py
djurls/utils.py
tests/mock/__init__.py
tests/mock/urls.py
tests/mock/views.py
