Metadata-Version: 2.0
Name: djURLs
Version: 0.0.2
Summary: Decorator for mapping Django URLs.
Home-page: https://github.com/victorfsf/djurls
Author: Victor Ferraz
Author-email: victorfsf.dev@gmail.com
License: UNKNOWN
Keywords: djurls,urls,urlpatterns,python,python2,python3,django
Platform: UNKNOWN
Classifier: Development Status :: 3 - Alpha
Classifier: Intended Audience :: Developers
Classifier: License :: OSI Approved :: MIT License
Classifier: Programming Language :: Python :: 2
Classifier: Programming Language :: Python :: 2.7
Classifier: Programming Language :: Python :: 3
Classifier: Programming Language :: Python :: 3.4
Classifier: Programming Language :: Python :: 3.5
Classifier: Framework :: Django
Classifier: Framework :: Django :: 1.7
Classifier: Framework :: Django :: 1.8
Classifier: Framework :: Django :: 1.9
